bert_tokens/__init__.py
bert_tokens/bert_tokenizer.py
bert_tokens/convert_word_span.py
bert_tokens/demo.py
bert_tokens-0.0.3.dist-info/LICENSE
bert_tokens-0.0.3.dist-info/METADATA
bert_tokens-0.0.3.dist-info/WHEEL
bert_tokens-0.0.3.dist-info/top_level.txt
bert_tokens-0.0.3.dist-info/RECORD
