Metadata-Version: 2.1
Name: bert-tokens
Version: 0.0.3
Summary: A useful tool for bert tokenization
Home-page: https://github.com/StefenSal/Bert-Tokens-Tools
Author: StefenSal
Author-email: 4772896@gmail.com
License: UNKNOWN
Platform: UNKNOWN
Classifier: Programming Language :: Python :: 3
Classifier: License :: OSI Approved :: MIT License
Classifier: Operating System :: OS Independent
